MyPackage/__init__.py
MyPackage/module1.py
MyPackage/module2.py
prachi_package_test-0.1.1.dist-info/LICENSE
prachi_package_test-0.1.1.dist-info/METADATA
prachi_package_test-0.1.1.dist-info/WHEEL
prachi_package_test-0.1.1.dist-info/top_level.txt
prachi_package_test-0.1.1.dist-info/RECORD
