Metadata-Version: 2.1
Name: prachi-package-test
Version: 0.1.1
Summary: Sample Test Package
Home-page: https://github.com/prachikabra121/prachi_package_test
Author: Prachi Kabra
Author-email: codebakery8889@gmail.com
Classifier: Programming Language :: Python :: 3
Classifier: License :: OSI Approved :: MIT License
Classifier: Operating System :: OS Independent
Requires-Python: >=3.6
License-File: LICENSE
